MANIFEST.in
README.rst
setup.py
tests/accessor/__init__.py
tests/accessor/test_playlist_items.py
tests/accessor/test_playlists.py
tests/helper/__init__.py
tests/helper/test_playlists.py
youtube_autodownloader.egg-info/PKG-INFO
youtube_autodownloader.egg-info/SOURCES.txt
youtube_autodownloader.egg-info/dependency_links.txt
youtube_autodownloader.egg-info/not-zip-safe
youtube_autodownloader.egg-info/requires.txt
youtube_autodownloader.egg-info/top_level.txt
ytad/__init__.py
ytad/client_manager.py
ytad/download.py
ytad/entity_registry.py
ytad/exceptions.py
ytad/pager.py
ytad/persisted.py
ytad/poll.py
ytad/test_support.py
ytad/utility.py
ytad/accessor/__init__.py
ytad/accessor/playlist_items.py
ytad/accessor/playlists.py
ytad/config/__init__.py
ytad/config/authorization.py
ytad/config/log.py
ytad/config/persisted.py
ytad/entity/__init__.py
ytad/entity/_entity_base.py
ytad/entity/_list_base.py
ytad/entity/playlist.py
ytad/entity/playlist_item.py
ytad/entity/playlist_item_list_response.py
ytad/entity/playlist_list_response.py
ytad/helper/__init__.py
ytad/helper/playlists.py
ytad/resources/README.rst
ytad/resources/requirements.txt
ytad/resources/version.txt
ytad/resources/scripts/ytad_autoauth
ytad/resources/scripts/ytad_autodownload
ytad/resources/scripts/ytad_manualauth_get_url
ytad/resources/scripts/ytad_manualauth_record_token
ytad/resources/scripts/ytad_search_playlists