Metadata-Version: 1.0
Name: youtube-autodownloader
Version: 0.2.6
Summary: Tool to auto-download new playlist entries.
Home-page: https://github.com/dsoprea/youtube-autodownloader
Author: Dustin Oprea
Author-email: dustin@randomingenuity.com
License: UNKNOWN
Keywords: youtube
Platform: UNKNOWN
